[{"metadata":{"name":"metallb-controller-85bd6857c7","namespace":"metallb-system","selfLink":"/apis/apps/v1/namespaces/metallb-system/replicasets/metallb-controller-85bd6857c7","uid":"f85ecbdc-d072-11e9-89b8-c400ad16bc2d","resourceVersion":"26452369","generation":1,"creationTimestamp":"2019-09-06T06:53:02Z","labels":{"app":"metallb","chart":"metallb-0.11.2","component":"controller","heritage":"Tiller","pod-template-hash":"4168241373","release":"metallb"},"annotations":{"deployment.kubernetes.io/desired-replicas":"1","deployment.kubernetes.io/max-replicas":"2","deployment.kubernetes.io/revision":"1"},"ownerReferences":[{"apiVersion":"apps/v1","kind":"Deployment","name":"metallb-controller","uid":"f846781b-d072-11e9-89b8-c400ad16bc2d","controller":true,"blockOwnerDeletion":true}]},"spec":{"replicas":1,"selector":{"matchLabels":{"app":"metallb","component":"controller","pod-template-hash":"4168241373","release":"metallb"}},"template":{"metadata":{"creationTimestamp":null,"labels":{"app":"metallb","chart":"metallb-0.11.2","component":"controller","heritage":"Tiller","pod-template-hash":"4168241373","release":"metallb"}},"spec":{"containers":[{"name":"controller","image":"metallb/controller:v0.8.1","args":["--port=7472","--config=metallb-config"],"ports":[{"name":"monitoring","containerPort":7472,"protocol":"TCP"}],"resources":{},"terminationMessagePath":"/dev/termination-log","terminationMessagePolicy":"File","imagePullPolicy":"IfNotPresent","securityContext":{"capabilities":{"drop":["all"]},"readOnlyRootFilesystem":true,"allowPrivilegeEscalation":false}}],"restartPolicy":"Always","terminationGracePeriodSeconds":0,"dnsPolicy":"ClusterFirst","nodeSelector":{"beta.kubernetes.io/os":"linux"},"serviceAccountName":"metallb-controller","serviceAccount":"metallb-controller","securityContext":{"runAsUser":65534,"runAsNonRoot":true},"schedulerName":"default-scheduler"}}},"status":{"replicas":1,"fullyLabeledReplicas":1,"readyReplicas":1,"availableReplicas":1,"observedGeneration":1}}]