[{"metadata":{"name":"chartmuseum-chartmuseum","namespace":"repository","selfLink":"/api/v1/namespaces/repository/persistentvolumeclaims/chartmuseum-chartmuseum","uid":"38618a48-c573-11e9-89b8-c400ad16bc2d","resourceVersion":"17285552","creationTimestamp":"2019-08-23T06:57:06Z","labels":{"app":"chartmuseum-chartmuseum","release":"chartmuseum"},"annotations":{"pv.kubernetes.io/bind-completed":"yes","pv.kubernetes.io/bound-by-controller":"yes","volume.beta.kubernetes.io/storage-provisioner":"kubernetes.io/rbd"},"finalizers":["kubernetes.io/pvc-protection"]},"spec":{"accessModes":["ReadWriteOnce"],"resources":{"requests":{"storage":"8Gi"}},"volumeName":"pvc-38618a48-c573-11e9-89b8-c400ad16bc2d","storageClassName":"rbd"},"status":{"phase":"Bound","accessModes":["ReadWriteOnce"],"capacity":{"storage":"8Gi"}}},{"metadata":{"name":"docker-registry","namespace":"repository","selfLink":"/api/v1/namespaces/repository/persistentvolumeclaims/docker-registry","uid":"80ded9ae-c971-11e9-89b8-c400ad16bc2d","resourceVersion":"18457572","creationTimestamp":"2019-08-28T08:54:54Z","labels":{"app":"docker-registry","chart":"docker-registry-1.8.5","heritage":"Tiller","release":"docker-registry"},"annotations":{"pv.kubernetes.io/bind-completed":"yes","pv.kubernetes.io/bound-by-controller":"yes","volume.beta.kubernetes.io/storage-provisioner":"kubernetes.io/rbd"},"finalizers":["kubernetes.io/pvc-protection"]},"spec":{"accessModes":["ReadWriteOnce"],"resources":{"requests":{"storage":"128Gi"}},"volumeName":"pvc-80ded9ae-c971-11e9-89b8-c400ad16bc2d","storageClassName":"rbd"},"status":{"phase":"Bound","accessModes":["ReadWriteOnce"],"capacity":{"storage":"128Gi"}}}]