[{"metadata":{"name":"grafana","selfLink":"/apis/extensions/v1beta1/podsecuritypolicies/grafana","uid":"2f0631ca-c96a-11e9-89b8-c400ad16bc2d","resourceVersion":"20286351","creationTimestamp":"2019-08-28T08:02:30Z","labels":{"app":"grafana","chart":"grafana-1.14.23","heritage":"Tiller","release":"grafana"},"annotations":{"apparmor.security.beta.kubernetes.io/allowedProfileNames":"runtime/default","apparmor.security.beta.kubernetes.io/defaultProfileName":"runtime/default","seccomp.security.alpha.kubernetes.io/allowedProfileNames":"docker/default","seccomp.security.alpha.kubernetes.io/defaultProfileName":"docker/default"}},"spec":{"requiredDropCapabilities":["ALL"],"volumes":["configMap","emptyDir","projected","secret","downwardAPI","persistentVolumeClaim"],"seLinux":{"rule":"RunAsAny"},"runAsUser":{"rule":"RunAsAny"},"supplementalGroups":{"rule":"RunAsAny"},"fsGroup":{"rule":"RunAsAny"},"allowPrivilegeEscalation":false}},{"metadata":{"name":"metallb-speaker","selfLink":"/apis/extensions/v1beta1/podsecuritypolicies/metallb-speaker","uid":"f7e0cf49-d072-11e9-89b8-c400ad16bc2d","resourceVersion":"20513527","creationTimestamp":"2019-09-06T06:53:01Z","labels":{"app":"metallb","chart":"metallb-0.11.2","heritage":"Tiller","release":"metallb"}},"spec":{"privileged":true,"allowedCapabilities":["NET_ADMIN","NET_RAW","SYS_ADMIN"],"volumes":["*"],"hostNetwork":true,"hostPorts":[{"min":7472,"max":7472}],"seLinux":{"rule":"RunAsAny"},"runAsUser":{"rule":"RunAsAny"},"supplementalGroups":{"rule":"RunAsAny"},"fsGroup":{"rule":"RunAsAny"},"allowPrivilegeEscalation":false}},{"metadata":{"name":"postgres-exporter","selfLink":"/apis/extensions/v1beta1/podsecuritypolicies/postgres-exporter","uid":"bf9f1cb4-ca06-11e9-89b8-c400ad16bc2d","resourceVersion":"18627416","creationTimestamp":"2019-08-29T02:43:14Z","labels":{"app":"postgres-exporter","chart":"postgres-exporter-0.6.6","heritage":"Tiller","release":"postgres-exporter"},"annotations":{"apparmor.security.beta.kubernetes.io/allowedProfileNames":"runtime/default","apparmor.security.beta.kubernetes.io/defaultProfileName":"runtime/default","seccomp.security.alpha.kubernetes.io/allowedProfileNames":"docker/default","seccomp.security.alpha.kubernetes.io/defaultProfileName":"docker/default"}},"spec":{"requiredDropCapabilities":["ALL"],"volumes":["configMap","emptyDir","projected","secret","downwardAPI"],"seLinux":{"rule":"RunAsAny"},"runAsUser":{"rule":"RunAsAny"},"supplementalGroups":{"rule":"RunAsAny"},"fsGroup":{"rule":"RunAsAny"},"allowPrivilegeEscalation":false}},{"metadata":{"name":"speaker","selfLink":"/apis/extensions/v1beta1/podsecuritypolicies/speaker","uid":"fdbabb88-ce1e-11e9-89b8-c400ad16bc2d","resourceVersion":"19830800","creationTimestamp":"2019-09-03T07:46:51Z","labels":{"app":"metallb"},"annotations":{"kubectl.kubernetes.io/last-applied-configuration":"{\"apiVersion\":\"policy/v1beta1\",\"kind\":\"PodSecurityPolicy\",\"metadata\":{\"annotations\":{},\"labels\":{\"app\":\"metallb\"},\"name\":\"speaker\",\"namespace\":\"\"},\"spec\":{\"allowPrivilegeEscalation\":false,\"allowedCapabilities\":[\"NET_ADMIN\",\"NET_RAW\",\"SYS_ADMIN\"],\"fsGroup\":{\"rule\":\"RunAsAny\"},\"hostNetwork\":true,\"hostPorts\":[{\"max\":7472,\"min\":7472}],\"privileged\":true,\"runAsUser\":{\"rule\":\"RunAsAny\"},\"seLinux\":{\"rule\":\"RunAsAny\"},\"supplementalGroups\":{\"rule\":\"RunAsAny\"},\"volumes\":[\"*\"]}}\n"}},"spec":{"privileged":true,"allowedCapabilities":["NET_ADMIN","NET_RAW","SYS_ADMIN"],"volumes":["*"],"hostNetwork":true,"hostPorts":[{"min":7472,"max":7472}],"seLinux":{"rule":"RunAsAny"},"runAsUser":{"rule":"RunAsAny"},"supplementalGroups":{"rule":"RunAsAny"},"fsGroup":{"rule":"RunAsAny"},"allowPrivilegeEscalation":false}}]