[{"metadata":{"name":"calico-kube-controllers","namespace":"kube-system","selfLink":"/apis/apps/v1/namespaces/kube-system/deployments/calico-kube-controllers","uid":"de8c46ee-76c0-11e9-a512-c400ad16bc2d","resourceVersion":"26452394","generation":1,"creationTimestamp":"2019-05-15T03:23:55Z","labels":{"k8s-app":"calico-kube-controllers","kubernetes.io/cluster-service":"true"},"annotations":{"deployment.kubernetes.io/revision":"1","kubectl.kubernetes.io/last-applied-configuration":"{\"apiVersion\":\"apps/v1beta2\",\"kind\":\"Deployment\",\"metadata\":{\"annotations\":{\"scheduler.alpha.kubernetes.io/critical-pod\":\"\"},\"labels\":{\"k8s-app\":\"calico-kube-controllers\",\"kubernetes.io/cluster-service\":\"true\"},\"name\":\"calico-kube-controllers\",\"namespace\":\"kube-system\"},\"spec\":{\"replicas\":1,\"selector\":{\"matchLabels\":{\"k8s-app\":\"calico-kube-controllers\",\"kubernetes.io/cluster-service\":\"true\"}},\"strategy\":{\"type\":\"RollingUpdate\"},\"template\":{\"metadata\":{\"labels\":{\"k8s-app\":\"calico-kube-controllers\",\"kubernetes.io/cluster-service\":\"true\"},\"name\":\"calico-kube-controllers\",\"namespace\":\"kube-system\"},\"spec\":{\"containers\":[{\"env\":[{\"name\":\"ETCD_ENDPOINTS\",\"value\":\"https://192.168.11.6:2379\"},{\"name\":\"ETCD_CA_CERT_FILE\",\"value\":\"/etc/calico/certs/ca_cert.crt\"},{\"name\":\"ETCD_CERT_FILE\",\"value\":\"/etc/calico/certs/cert.crt\"},{\"name\":\"ETCD_KEY_FILE\",\"value\":\"/etc/calico/certs/key.pem\"}],\"image\":\"ecgwc/kube-controllers:v3.1.3\",\"imagePullPolicy\":\"IfNotPresent\",\"name\":\"calico-kube-controllers\",\"resources\":{\"limits\":{\"cpu\":\"100m\",\"memory\":\"256M\"},\"requests\":{\"cpu\":\"30m\",\"memory\":\"64M\"}},\"volumeMounts\":[{\"mountPath\":\"/etc/calico/certs\",\"name\":\"etcd-certs\",\"readOnly\":true}]}],\"hostNetwork\":true,\"priorityClassName\":\"system-cluster-critical\",\"serviceAccountName\":\"calico-kube-controllers\",\"tolerations\":[{\"effect\":\"NoSchedule\",\"operator\":\"Exists\"}],\"volumes\":[{\"hostPath\":{\"path\":\"/etc/calico/certs\"},\"name\":\"etcd-certs\"}]}}}}\n","scheduler.alpha.kubernetes.io/critical-pod":""}},"spec":{"replicas":1,"selector":{"matchLabels":{"k8s-app":"calico-kube-controllers","kubernetes.io/cluster-service":"true"}},"template":{"metadata":{"name":"calico-kube-controllers","namespace":"kube-system","creationTimestamp":null,"labels":{"k8s-app":"calico-kube-controllers","kubernetes.io/cluster-service":"true"}},"spec":{"volumes":[{"name":"etcd-certs","hostPath":{"path":"/etc/calico/certs","type":""}}],"containers":[{"name":"calico-kube-controllers","image":"ecgwc/kube-controllers:v3.1.3","env":[{"name":"ETCD_ENDPOINTS","value":"https://192.168.11.6:2379"},{"name":"ETCD_CA_CERT_FILE","value":"/etc/calico/certs/ca_cert.crt"},{"name":"ETCD_CERT_FILE","value":"/etc/calico/certs/cert.crt"},{"name":"ETCD_KEY_FILE","value":"/etc/calico/certs/key.pem"}],"resources":{"limits":{"cpu":"100m","memory":"256M"},"requests":{"cpu":"30m","memory":"64M"}},"volumeMounts":[{"name":"etcd-certs","readOnly":true,"mountPath":"/etc/calico/certs"}],"terminationMessagePath":"/dev/termination-log","terminationMessagePolicy":"File","imagePullPolicy":"IfNotPresent"}],"restartPolicy":"Always","terminationGracePeriodSeconds":30,"dnsPolicy":"ClusterFirst","serviceAccountName":"calico-kube-controllers","serviceAccount":"calico-kube-controllers","hostNetwork":true,"securityContext":{},"schedulerName":"default-scheduler","tolerations":[{"operator":"Exists","effect":"NoSchedule"}],"priorityClassName":"system-cluster-critical"}},"strategy":{"type":"RollingUpdate","rollingUpdate":{"maxUnavailable":"25%","maxSurge":"25%"}},"revisionHistoryLimit":10,"progressDeadlineSeconds":600},"status":{"observedGeneration":1,"replicas":1,"updatedReplicas":1,"readyReplicas":1,"availableReplicas":1,"conditions":[{"type":"Progressing","status":"True","lastUpdateTime":"2019-05-15T03:23:58Z","lastTransitionTime":"2019-05-15T03:23:55Z","reason":"NewReplicaSetAvailable","message":"ReplicaSet \"calico-kube-controllers-55fcdc5bdb\" has successfully progressed."},{"type":"Available","status":"True","lastUpdateTime":"2019-10-02T03:39:14Z","lastTransitionTime":"2019-10-02T03:39:14Z","reason":"MinimumReplicasAvailable","message":"Deployment has minimum availability."}]}},{"metadata":{"name":"cert-manager","namespace":"kube-system","selfLink":"/apis/apps/v1/namespaces/kube-system/deployments/cert-manager","uid":"01f2ef69-90c5-11e9-b69a-c400ad16bc2d","resourceVersion":"26452409","generation":1,"creationTimestamp":"2019-06-17T05:59:02Z","labels":{"app":"cert-manager","chart":"cert-manager-v0.5.2","heritage":"Tiller","release":"cert-manager"},"annotations":{"deployment.kubernetes.io/revision":"1"}},"spec":{"replicas":1,"selector":{"matchLabels":{"app":"cert-manager","release":"cert-manager"}},"template":{"metadata":{"creationTimestamp":null,"labels":{"app":"cert-manager","release":"cert-manager"}},"spec":{"containers":[{"name":"cert-manager","image":"quay.io/jetstack/cert-manager-controller:v0.5.2","args":["--cluster-resource-namespace=$(POD_NAMESPACE)","--leader-election-namespace=$(POD_NAMESPACE)"],"env":[{"name":"POD_NAMESPACE","valueFrom":{"fieldRef":{"apiVersion":"v1","fieldPath":"metadata.namespace"}}}],"resources":{},"terminationMessagePath":"/dev/termination-log","terminationMessagePolicy":"File","imagePullPolicy":"IfNotPresent"}],"restartPolicy":"Always","terminationGracePeriodSeconds":30,"dnsPolicy":"ClusterFirst","serviceAccountName":"cert-manager","serviceAccount":"cert-manager","securityContext":{},"schedulerName":"default-scheduler"}},"strategy":{"type":"RollingUpdate","rollingUpdate":{"maxUnavailable":"25%","maxSurge":"25%"}},"revisionHistoryLimit":2,"progressDeadlineSeconds":600},"status":{"observedGeneration":1,"replicas":1,"updatedReplicas":1,"readyReplicas":1,"availableReplicas":1,"conditions":[{"type":"Progressing","status":"True","lastUpdateTime":"2019-06-17T05:59:13Z","lastTransitionTime":"2019-06-17T05:59:02Z","reason":"NewReplicaSetAvailable","message":"ReplicaSet \"cert-manager-7d4bfc44ff\" has successfully progressed."},{"type":"Available","status":"True","lastUpdateTime":"2019-10-02T03:39:16Z","lastTransitionTime":"2019-10-02T03:39:16Z","reason":"MinimumReplicasAvailable","message":"Deployment has minimum availability."}]}},{"metadata":{"name":"coredns","namespace":"kube-system","selfLink":"/apis/apps/v1/namespaces/kube-system/deployments/coredns","uid":"eaa16112-76c0-11e9-a512-c400ad16bc2d","resourceVersion":"26454184","generation":1,"creationTimestamp":"2019-05-15T03:24:15Z","labels":{"addonmanager.kubernetes.io/mode":"Reconcile","k8s-app":"coredns","kubernetes.io/cluster-service":"true","kubernetes.io/name":"CoreDNS"},"annotations":{"deployment.kubernetes.io/revision":"1","kubectl.kubernetes.io/last-applied-configuration":"{\"apiVersion\":\"extensions/v1beta1\",\"kind\":\"Deployment\",\"metadata\":{\"annotations\":{},\"labels\":{\"addonmanager.kubernetes.io/mode\":\"Reconcile\",\"k8s-app\":\"coredns\",\"kubernetes.io/cluster-service\":\"true\",\"kubernetes.io/name\":\"CoreDNS\"},\"name\":\"coredns\",\"namespace\":\"kube-system\"},\"spec\":{\"replicas\":2,\"selector\":{\"matchLabels\":{\"k8s-app\":\"coredns\"}},\"strategy\":{\"rollingUpdate\":{\"maxSurge\":\"10%\",\"maxUnavailable\":0},\"type\":\"RollingUpdate\"},\"template\":{\"metadata\":{\"annotations\":{\"scheduler.alpha.kubernetes.io/critical-pod\":\"\"},\"labels\":{\"k8s-app\":\"coredns\"}},\"spec\":{\"affinity\":{\"nodeAffinity\":{\"preferredDuringSchedulingIgnoredDuringExecution\":[{\"preference\":{\"matchExpressions\":[{\"key\":\"node-role.kubernetes.io/master\",\"operator\":\"In\",\"values\":[\"true\"]}]},\"weight\":100}]},\"podAntiAffinity\":{\"requiredDuringSchedulingIgnoredDuringExecution\":[{\"labelSelector\":{\"matchLabels\":{\"k8s-app\":\"coredns\"}},\"topologyKey\":\"kubernetes.io/hostname\"}]}},\"containers\":[{\"args\":[\"-conf\",\"/etc/coredns/Corefile\"],\"image\":\"ecgwc/coredns:1.2.2\",\"imagePullPolicy\":\"IfNotPresent\",\"livenessProbe\":{\"failureThreshold\":5,\"httpGet\":{\"path\":\"/health\",\"port\":8080,\"scheme\":\"HTTP\"},\"initialDelaySeconds\":60,\"successThreshold\":1,\"timeoutSeconds\":5},\"name\":\"coredns\",\"ports\":[{\"containerPort\":53,\"name\":\"dns\",\"protocol\":\"UDP\"},{\"containerPort\":53,\"name\":\"dns-tcp\",\"protocol\":\"TCP\"},{\"containerPort\":9153,\"name\":\"metrics\",\"protocol\":\"TCP\"}],\"resources\":{\"limits\":{\"memory\":\"170Mi\"},\"requests\":{\"cpu\":\"100m\",\"memory\":\"70Mi\"}},\"volumeMounts\":[{\"mountPath\":\"/etc/coredns\",\"name\":\"config-volume\"}]}],\"dnsPolicy\":\"Default\",\"priorityClassName\":\"system-cluster-critical\",\"serviceAccountName\":\"coredns\",\"tolerations\":[{\"effect\":\"NoSchedule\",\"key\":\"node-role.kubernetes.io/master\"},{\"key\":\"CriticalAddonsOnly\",\"operator\":\"Exists\"}],\"volumes\":[{\"configMap\":{\"items\":[{\"key\":\"Corefile\",\"path\":\"Corefile\"}],\"name\":\"coredns\"},\"name\":\"config-volume\"}]}}}}\n"}},"spec":{"replicas":2,"selector":{"matchLabels":{"k8s-app":"coredns"}},"template":{"metadata":{"creationTimestamp":null,"labels":{"k8s-app":"coredns"},"annotations":{"scheduler.alpha.kubernetes.io/critical-pod":""}},"spec":{"volumes":[{"name":"config-volume","configMap":{"name":"coredns","items":[{"key":"Corefile","path":"Corefile"}],"defaultMode":420}}],"containers":[{"name":"coredns","image":"ecgwc/coredns:1.2.2","args":["-conf","/etc/coredns/Corefile"],"ports":[{"name":"dns","containerPort":53,"protocol":"UDP"},{"name":"dns-tcp","containerPort":53,"protocol":"TCP"},{"name":"metrics","containerPort":9153,"protocol":"TCP"}],"resources":{"limits":{"memory":"170Mi"},"requests":{"cpu":"100m","memory":"70Mi"}},"volumeMounts":[{"name":"config-volume","mountPath":"/etc/coredns"}],"livenessProbe":{"httpGet":{"path":"/health","port":8080,"scheme":"HTTP"},"initialDelaySeconds":60,"timeoutSeconds":5,"periodSeconds":10,"successThreshold":1,"failureThreshold":5},"terminationMessagePath":"/dev/termination-log","terminationMessagePolicy":"File","imagePullPolicy":"IfNotPresent"}],"restartPolicy":"Always","terminationGracePeriodSeconds":30,"dnsPolicy":"Default","serviceAccountName":"coredns","serviceAccount":"coredns","securityContext":{},"affinity":{"nodeAffinity":{"preferredDuringSchedulingIgnoredDuringExecution":[{"weight":100,"preference":{"matchExpressions":[{"key":"node-role.kubernetes.io/master","operator":"In","values":["true"]}]}}]},"podAntiAffinity":{"requiredDuringSchedulingIgnoredDuringExecution":[{"labelSelector":{"matchLabels":{"k8s-app":"coredns"}},"topologyKey":"kubernetes.io/hostname"}]}},"schedulerName":"default-scheduler","tolerations":[{"key":"node-role.kubernetes.io/master","effect":"NoSchedule"},{"key":"CriticalAddonsOnly","operator":"Exists"}],"priorityClassName":"system-cluster-critical"}},"strategy":{"type":"RollingUpdate","rollingUpdate":{"maxUnavailable":0,"maxSurge":"10%"}},"revisionHistoryLimit":10,"progressDeadlineSeconds":600},"status":{"observedGeneration":1,"replicas":2,"updatedReplicas":2,"readyReplicas":1,"availableReplicas":1,"unavailableReplicas":1,"conditions":[{"type":"Available","status":"False","lastUpdateTime":"2019-05-15T03:24:15Z","lastTransitionTime":"2019-05-15T03:24:15Z","reason":"MinimumReplicasUnavailable","message":"Deployment does not have minimum availability."},{"type":"Progressing","status":"False","lastUpdateTime":"2019-10-02T03:49:20Z","lastTransitionTime":"2019-10-02T03:49:20Z","reason":"ProgressDeadlineExceeded","message":"ReplicaSet \"coredns-7c949f49d5\" has timed out progressing."}]}},{"metadata":{"name":"kubernetes-dashboard","namespace":"kube-system","selfLink":"/apis/apps/v1/namespaces/kube-system/deployments/kubernetes-dashboard","uid":"ecc4459a-76c0-11e9-a512-c400ad16bc2d","resourceVersion":"26452406","generation":2,"creationTimestamp":"2019-05-15T03:24:18Z","labels":{"k8s-app":"kubernetes-dashboard"},"annotations":{"deployment.kubernetes.io/revision":"2","kubectl.kubernetes.io/last-applied-configuration":"{\"apiVersion\":\"apps/v1beta2\",\"kind\":\"Deployment\",\"metadata\":{\"annotations\":{},\"labels\":{\"k8s-app\":\"kubernetes-dashboard\"},\"name\":\"kubernetes-dashboard\",\"namespace\":\"kube-system\"},\"spec\":{\"replicas\":1,\"revisionHistoryLimit\":10,\"selector\":{\"matchLabels\":{\"k8s-app\":\"kubernetes-dashboard\"}},\"template\":{\"metadata\":{\"labels\":{\"k8s-app\":\"kubernetes-dashboard\"}},\"spec\":{\"containers\":[{\"args\":[\"--auto-generate-certificates\",\"--authentication-mode=token\",\"--token-ttl=900\"],\"image\":\"gcr.io/google_containers/kubernetes-dashboard-amd64:v1.10.0\",\"imagePullPolicy\":\"IfNotPresent\",\"livenessProbe\":{\"httpGet\":{\"path\":\"/\",\"port\":8443,\"scheme\":\"HTTPS\"},\"initialDelaySeconds\":30,\"timeoutSeconds\":30},\"name\":\"kubernetes-dashboard\",\"ports\":[{\"containerPort\":8443,\"protocol\":\"TCP\"}],\"resources\":{\"limits\":{\"cpu\":\"100m\",\"memory\":\"256M\"},\"requests\":{\"cpu\":\"50m\",\"memory\":\"64M\"}},\"volumeMounts\":[{\"mountPath\":\"/certs\",\"name\":\"kubernetes-dashboard-certs\"},{\"mountPath\":\"/tmp\",\"name\":\"tmp-volume\"}]}],\"priorityClassName\":\"system-cluster-critical\",\"serviceAccountName\":\"kubernetes-dashboard\",\"tolerations\":[{\"effect\":\"NoSchedule\",\"key\":\"node-role.kubernetes.io/master\"}],\"volumes\":[{\"name\":\"kubernetes-dashboard-certs\",\"secret\":{\"secretName\":\"kubernetes-dashboard-certs\"}},{\"emptyDir\":{},\"name\":\"tmp-volume\"}]}}}}\n"}},"spec":{"replicas":1,"selector":{"matchLabels":{"k8s-app":"kubernetes-dashboard"}},"template":{"metadata":{"creationTimestamp":null,"labels":{"k8s-app":"kubernetes-dashboard"}},"spec":{"volumes":[{"name":"kubernetes-dashboard-certs","secret":{"secretName":"kubernetes-dashboard-certs","defaultMode":420}},{"name":"tmp-volume","emptyDir":{}}],"containers":[{"name":"kubernetes-dashboard","image":"gcr.io/google_containers/kubernetes-dashboard-amd64:v1.10.0","args":["--auto-generate-certificates","--authentication-mode=basic","--token-ttl=900"],"ports":[{"containerPort":8443,"protocol":"TCP"}],"resources":{"limits":{"cpu":"100m","memory":"256M"},"requests":{"cpu":"50m","memory":"64M"}},"volumeMounts":[{"name":"kubernetes-dashboard-certs","mountPath":"/certs"},{"name":"tmp-volume","mountPath":"/tmp"}],"livenessProbe":{"httpGet":{"path":"/","port":8443,"scheme":"HTTPS"},"initialDelaySeconds":30,"timeoutSeconds":30,"periodSeconds":10,"successThreshold":1,"failureThreshold":3},"terminationMessagePath":"/dev/termination-log","terminationMessagePolicy":"File","imagePullPolicy":"IfNotPresent"}],"restartPolicy":"Always","terminationGracePeriodSeconds":30,"dnsPolicy":"ClusterFirst","serviceAccountName":"kubernetes-dashboard","serviceAccount":"kubernetes-dashboard","securityContext":{},"schedulerName":"default-scheduler","tolerations":[{"key":"node-role.kubernetes.io/master","effect":"NoSchedule"}],"priorityClassName":"system-cluster-critical"}},"strategy":{"type":"RollingUpdate","rollingUpdate":{"maxUnavailable":"25%","maxSurge":"25%"}},"revisionHistoryLimit":10,"progressDeadlineSeconds":600},"status":{"observedGeneration":2,"replicas":1,"updatedReplicas":1,"readyReplicas":1,"availableReplicas":1,"conditions":[{"type":"Progressing","status":"True","lastUpdateTime":"2019-06-17T01:52:30Z","lastTransitionTime":"2019-05-15T03:24:18Z","reason":"NewReplicaSetAvailable","message":"ReplicaSet \"kubernetes-dashboard-6c4587f67d\" has successfully progressed."},{"type":"Available","status":"True","lastUpdateTime":"2019-10-02T03:39:16Z","lastTransitionTime":"2019-10-02T03:39:16Z","reason":"MinimumReplicasAvailable","message":"Deployment has minimum availability."}]}},{"metadata":{"name":"tiller-deploy","namespace":"kube-system","selfLink":"/apis/apps/v1/namespaces/kube-system/deployments/tiller-deploy","uid":"f2db2056-76c0-11e9-a512-c400ad16bc2d","resourceVersion":"26452413","generation":4,"creationTimestamp":"2019-05-15T03:24:29Z","labels":{"app":"helm","name":"tiller"},"annotations":{"deployment.kubernetes.io/revision":"4"}},"spec":{"replicas":1,"selector":{"matchLabels":{"app":"helm","name":"tiller"}},"template":{"metadata":{"creationTimestamp":null,"labels":{"app":"helm","name":"tiller"}},"spec":{"containers":[{"name":"tiller","image":"gcr.io/kubernetes-helm/tiller:v2.14.1","ports":[{"name":"tiller","containerPort":44134,"protocol":"TCP"},{"name":"http","containerPort":44135,"protocol":"TCP"}],"env":[{"name":"TILLER_NAMESPACE","value":"kube-system"},{"name":"TILLER_HISTORY_MAX","value":"0"}],"resources":{},"livenessProbe":{"httpGet":{"path":"/liveness","port":44135,"scheme":"HTTP"},"initialDelaySeconds":1,"timeoutSeconds":1,"periodSeconds":10,"successThreshold":1,"failureThreshold":3},"readinessProbe":{"httpGet":{"path":"/readiness","port":44135,"scheme":"HTTP"},"initialDelaySeconds":1,"timeoutSeconds":1,"periodSeconds":10,"successThreshold":1,"failureThreshold":3},"terminationMessagePath":"/dev/termination-log","terminationMessagePolicy":"File","imagePullPolicy":"IfNotPresent"}],"restartPolicy":"Always","terminationGracePeriodSeconds":30,"dnsPolicy":"ClusterFirst","serviceAccountName":"tiller","serviceAccount":"tiller","securityContext":{},"schedulerName":"default-scheduler"}},"strategy":{"type":"RollingUpdate","rollingUpdate":{"maxUnavailable":1,"maxSurge":1}},"revisionHistoryLimit":10,"progressDeadlineSeconds":600},"status":{"observedGeneration":4,"replicas":1,"updatedReplicas":1,"readyReplicas":1,"availableReplicas":1,"conditions":[{"type":"Available","status":"True","lastUpdateTime":"2019-05-15T03:24:29Z","lastTransitionTime":"2019-05-15T03:24:29Z","reason":"MinimumReplicasAvailable","message":"Deployment has minimum availability."},{"type":"Progressing","status":"True","lastUpdateTime":"2019-07-01T08:58:15Z","lastTransitionTime":"2019-05-15T03:24:29Z","reason":"NewReplicaSetAvailable","message":"ReplicaSet \"tiller-deploy-7f554d9fd7\" has successfully progressed."}]}}]